rqalpha_mod_log/__init__.py
rqalpha_mod_log/mod.py
rqalpha_mod_log-0.1.3.dist-info/LICENSE
rqalpha_mod_log-0.1.3.dist-info/METADATA
rqalpha_mod_log-0.1.3.dist-info/WHEEL
rqalpha_mod_log-0.1.3.dist-info/top_level.txt
rqalpha_mod_log-0.1.3.dist-info/RECORD
