Metadata-Version: 2.1
Name: rqalpha-mod-log
Version: 0.1.3
Summary: RQAlpha Mod for logbook
Home-page: https://github.com/lawrentchen/rqalpha-mod-log
Author: LawrentChen
Author-email: laurant.chen@gmail.com
License: UNKNOWN
Platform: UNKNOWN
Classifier: Programming Language :: Python :: 3
Classifier: License :: OSI Approved :: MIT License
Classifier: Operating System :: OS Independent
Requires-Python: >=3.6
License-File: LICENSE
